dkist/__init__.py
dkist/_version.py
dkist/conftest.py
dkist/dkist.cfg
dkist/logger.py
dkist/version.py
dkist/config/__init__.py
dkist/data/README.rst
dkist/data/VISP_HEADER.hdr
dkist/data/__init__.py
dkist/data/_sample.py
dkist/data/api_search_values.json
dkist/data/sample.py
dkist/data/test/5d_gwcs.asdf
dkist/data/test/AGLKO-inv.ecsv
dkist/data/test/__init__.py
dkist/data/test/croppable_cryo.asdf.gz
dkist/data/test/croppable_visp.asdf.gz
dkist/data/test/eit_dataset-0.1.0.asdf
dkist/data/test/eit_dataset-0.2.0.asdf
dkist/data/test/eit_dataset-0.3.0.asdf
dkist/data/test/eit_dataset-1.0.0.asdf
dkist/data/test/eit_dataset-1.1.0.asdf
dkist/data/test/eit_dataset-1.2.0.asdf
dkist/data/test/globus_operation_ls_response.json
dkist/data/test/globus_search_response.json
dkist/data/test/large_vbi.asdf.gz
dkist/data/test/large_visp.asdf.gz
dkist/data/test/test_old_wcs_BRMQY.asdf
dkist/data/test/test_tiled_dataset-1.0.0_dataset-1.0.0.asdf
dkist/data/test/test_tiled_dataset-1.0.0_dataset-1.1.0.asdf
dkist/data/test/test_tiled_dataset-1.0.0_dataset-1.2.0.asdf
dkist/data/test/test_tiled_dataset-1.1.0_dataset-1.2.0.asdf
dkist/data/test/test_tiled_dataset-1.2.0_dataset-1.2.0.asdf
dkist/data/test/test_tiled_dataset-1.3.0_dataset-1.2.0.asdf
dkist/data/test/visp_no_headers.asdf.gz
dkist/data/test/EIT/efz20040301.000010_s.fits
dkist/data/test/EIT/efz20040301.020010_s.fits
dkist/data/test/EIT/efz20040301.030011_s.fits
dkist/data/test/EIT/efz20040301.040010_s.fits
dkist/data/test/EIT/efz20040301.050010_s.fits
dkist/data/test/EIT/efz20040301.060010_s.fits
dkist/data/test/EIT/efz20040301.080010_s.fits
dkist/data/test/EIT/efz20040301.090010_s.fits
dkist/data/test/EIT/efz20040301.100010_s.fits
dkist/data/test/EIT/efz20040301.110010_s.fits
dkist/data/test/EIT/efz20040301.120010_s.fits
dkist/data/test/EIT/eit_test_dataset.asdf
dkist/data/test/small_visp/0.fits
dkist/data/test/small_visp/1.fits
dkist/data/test/small_visp/2.fits
dkist/data/test/small_visp/test_visp.asdf
dkist-1.16.0.dist-info/licenses/LICENSE.rst
dkist-1.16.0.dist-info/METADATA
dkist-1.16.0.dist-info/WHEEL
dkist-1.16.0.dist-info/entry_points.txt
dkist-1.16.0.dist-info/top_level.txt
dkist-1.16.0.dist-info/RECORD
