Metadata-Version: 2.4
Name: dkist
Version: 1.16.0
Summary: DKIST User Tools
Author-email: NSO / AURA <stuart@cadair.com>
Project-URL: Homepage, https://github.com/DKISTDC/dkist
Project-URL: Source Code, https://github.com/DKISTDC/dkist
Project-URL: Download, https://pypi.org/project/dkist
Project-URL: Documentation, https://docs.dkist.nso.edu/projects/python-tools/en/stable/
Project-URL: Changelog, https://docs.dkist.nso.edu/projects/python-tools/en/stable/whatsnew/changelog.html
Project-URL: Issue Tracker, https://github.com/DKISTDC/dkist/issues
Requires-Python: >=3.11
License-File: LICENSE.rst
Requires-Dist: aiohttp>=3.9
Requires-Dist: asdf>=3.3.0
Requires-Dist: asdf-astropy>=0.5.0
Requires-Dist: asdf-coordinates-schemas>=0.3.0
Requires-Dist: asdf-standard>=1.1.0
Requires-Dist: asdf-transform-schemas>=0.6.0
Requires-Dist: asdf-wcs-schemas>=0.4.0
Requires-Dist: astropy>=6.0
Requires-Dist: dask[array]>=2023.2.0
Requires-Dist: globus-sdk>=3.0
Requires-Dist: gwcs>=0.24.0
Requires-Dist: matplotlib>=3.7
Requires-Dist: ndcube[plotting,reproject]>=2.1
Requires-Dist: numpy>=1.25
Requires-Dist: parfive[ftp]>=2.2.0
Requires-Dist: platformdirs>=3.0
Requires-Dist: packaging>=23.0
Requires-Dist: sunpy[asdf,net]>=5.0.7
Requires-Dist: tqdm>=4.65
Provides-Extra: tests
Requires-Dist: pytest; extra == "tests"
Requires-Dist: pytest-asdf-plugin; extra == "tests"
Requires-Dist: pytest-doctestplus; extra == "tests"
Requires-Dist: pytest-cov; extra == "tests"
Requires-Dist: pytest-remotedata; extra == "tests"
Requires-Dist: pytest-mock; extra == "tests"
Requires-Dist: pytest-mpl; extra == "tests"
Requires-Dist: pytest-httpserver; extra == "tests"
Requires-Dist: pytest-filter-subpackage; extra == "tests"
Requires-Dist: pytest-benchmark; extra == "tests"
Requires-Dist: pytest-xdist; extra == "tests"
Requires-Dist: pytest-lazy-fixtures; extra == "tests"
Requires-Dist: hypothesis; extra == "tests"
Requires-Dist: tox; extra == "tests"
Requires-Dist: pydot; extra == "tests"
Provides-Extra: docs
Requires-Dist: sphinx; extra == "docs"
Requires-Dist: sphinx-automodapi; extra == "docs"
Requires-Dist: sphinx-changelog; extra == "docs"
Requires-Dist: sunpy-sphinx-theme; extra == "docs"
Requires-Dist: sphinx-astropy; extra == "docs"
Requires-Dist: sphinx-gallery; extra == "docs"
Requires-Dist: pytest; extra == "docs"
Requires-Dist: sphinx_autodoc_typehints; extra == "docs"
Requires-Dist: dkist-sphinx-theme>=2.0; extra == "docs"
Requires-Dist: sphinx-design; extra == "docs"
Requires-Dist: myst-nb; extra == "docs"
Requires-Dist: ipywidgets; extra == "docs"
Requires-Dist: accessible-pygments; extra == "docs"
Requires-Dist: reproject[all]; extra == "docs"
Requires-Dist: sunpy[asdf,net]>=6.1.0; extra == "docs"
Requires-Dist: snowballstemmer<3; extra == "docs"
Requires-Dist: distributed; extra == "docs"
Dynamic: license-file
